data_visualization/__init__.py
data_visualization/register.py
data_visualization/frontend/dist/index.html
data_visualization/frontend/dist/vite.svg
data_visualization/frontend/dist/assets/index-d081bea5.css
data_visualization/frontend/dist/assets/index-fc1e11f7.js
bp_data_visualization-1.0.5.dist-info/LICENSE
bp_data_visualization-1.0.5.dist-info/METADATA
bp_data_visualization-1.0.5.dist-info/WHEEL
bp_data_visualization-1.0.5.dist-info/top_level.txt
bp_data_visualization-1.0.5.dist-info/RECORD
