Metadata-Version: 2.1
Name: bp-data-visualization
Version: 1.0.5
Summary: Show data in charts
Home-page: UNKNOWN
Author: Bluepinapple
Author-email: viveksthul@bluepinapple.com
License: UNKNOWN
Platform: UNKNOWN
Requires-Python: >=3.8.10
Requires-Dist: streamlit (>=1.20.0)
